linz_logger/__init__.py
linz_logger/logger.py
linz_logger/test_logger.py
linz_logger-0.11.0.dist-info/LICENSE
linz_logger-0.11.0.dist-info/WHEEL
linz_logger-0.11.0.dist-info/METADATA
linz_logger-0.11.0.dist-info/RECORD
