Metadata-Version: 2.1
Name: linz-logger
Version: 0.11.0
Summary: LINZ standard Logging format
Home-page: https://github.com/linz/python-linz-logger
License: MIT
Keywords: LINZ,logging
Author: Blayne
Author-email: bchard@linz.govt.nz
Requires-Python: >=3.8,<4.0
Classifier: License :: OSI Approved :: MIT License
Classifier: Programming Language :: Python :: 3
Classifier: Programming Language :: Python :: 3.8
Classifier: Programming Language :: Python :: 3.9
Classifier: Programming Language :: Python :: 3.10
Classifier: Programming Language :: Python :: 3.11
Requires-Dist: python-ulid (>=1.1.0,<2.0.0)
Requires-Dist: structlog (>=22.1.0,<23.0.0)
Project-URL: Repository, https://github.com/linz/python-linz-logger
